HDL/core/pipeline.v
module pipeline#(
                 parameter UNSIGNED_INPUT_WIDTH = 16,
                 parameter UNSIGNED_OUTPUT_WIDTH = 16,
                 parameter UNSIGNED_INPUT_INT_WIDTH = 7,
                 parameter UNSIGNED_INPUT_FRAC_WIDTH = 8,
                 parameter UNSIGNED_OUTPUT_INT_WIDTH = 7,
                 parameter UNSIGNED_OUTPUT_FRAC_WIDTH = 8,
                 parameter ITERATION_NUMBER = 6,
                 parameter ITERATION_WORD_WIDTH = 32,
                 parameter ITERATION_WORD_INT_WIDTH = 12,
                 parameter ITERATION_WORD_FRAC_WIDTH = 20,
                 parameter SECTOR_FLAG_WIDTH = 2
                 )(
                   input wire                                  clk,
                   input wire                                  reset,
                   input wire signed [UNSIGNED_INPUT_WIDTH - 1 : 0]   degree_in,

                   input wire signed [UNSIGNED_INPUT_WIDTH - 1 : 0]   x_in,
                   input wire signed [UNSIGNED_INPUT_WIDTH - 1 : 0]   y_in,

                   input wire [SECTOR_FLAG_WIDTH - 1 : 0]      sector_in,
                   input wire                                  arctan_en_in,
                   input wire                                  valid_in,
                   output wire signed [UNSIGNED_OUTPUT_WIDTH - 1 : 0] degree_out,
                   output wire signed [UNSIGNED_OUTPUT_WIDTH - 1 : 0] x_out,
                   output wire signed [UNSIGNED_OUTPUT_WIDTH - 1 : 0] y_out,
                   output wire [SECTOR_FLAG_WIDTH - 1 : 0]     sector_out,
                   output wire                                 arctan_en_out,
                   output wire                                 valid_out
                   );
   /*
    TAN(*)  | DEG         | DEG (BIN)
    1       | 45          | 101101.000000000000000000000000000000000000000000000000000000000000000000
    0.5     | 26.56505118 | 11010.1001000010100111001100011010011000011101110000111100111111101001101
    0.25    | 14.03624347 | 1110.00001001010001110100000001111101011100000001011011110111100000011111
    0.125   | 7.123016349 | 111.001000000000000100010010010010011111111110100000101101101010101101100
    0.0625  | 3.576334375 | 11.1001001110001010101001100100110000101100100110011101110011101111000111
    0.03125 | 1.789910608 | 1.11001010001101111001010011100101001011100010101001111001001110011100110
    */
   /*
    TODO: Enlarge pipeline depth to 14
    */

   wire signed [ITERATION_WORD_WIDTH - 1 : 0]                         degree_mem [ITERATION_NUMBER - 1 : 0];
   // degree_mem[0] = 32'b000000101101 00000000000000000000;
   // degree_mem[1] = 32'b000000011010 10010000101001110011;
   // degree_mem[2] = 32'b000000001110 00001001010001110100;
   // degree_mem[3] = 32'b000000000111 00100000000000010001;
   // degree_mem[4] = 32'b000000000011 10010011100010101010;
   // degree_mem[5] = 32'b000000000001 11001010001101111001;
   assign degree_mem[0] = 32'b00000010110100000000000000000000;
   assign degree_mem[1] = 32'b00000001101010010000101001110011;
   assign degree_mem[2] = 32'b00000000111000001001010001110100;
   assign degree_mem[3] = 32'b00000000011100100000000000010001;
   assign degree_mem[4] = 32'b00000000001110010011100010101010;
   assign degree_mem[5] = 32'b00000000000111001010001101111001;


   reg signed [ITERATION_WORD_WIDTH - 1 : 0]                          degree_reg [ITERATION_NUMBER : 0];
   reg signed [ITERATION_WORD_WIDTH - 1 : 0]                          degree_approx_reg [ITERATION_NUMBER : 0];
   reg signed [ITERATION_WORD_WIDTH - 1 : 0]                          x_reg [ITERATION_NUMBER : 0];
   reg signed [ITERATION_WORD_WIDTH - 1 : 0]                          y_reg [ITERATION_NUMBER : 0];

   reg                                                                arctan_en_reg [ITERATION_NUMBER : 0];
   reg [SECTOR_FLAG_WIDTH - 1 : 0]                                    sector_reg [ITERATION_NUMBER : 0];
   reg                                                                valid_reg [ITERATION_NUMBER : 0];

   always @ *
     begin
        degree_reg[0][ITERATION_WORD_FRAC_WIDTH + UNSIGNED_INPUT_INT_WIDTH - 1 : ITERATION_WORD_FRAC_WIDTH - UNSIGNED_INPUT_FRAC_WIDTH] = degree_in;
        degree_reg[0][ITERATION_WORD_WIDTH - 1 : ITERATION_WORD_FRAC_WIDTH + UNSIGNED_INPUT_INT_WIDTH] = 0;
        degree_reg[0][ITERATION_WORD_FRAC_WIDTH - UNSIGNED_INPUT_FRAC_WIDTH - 1 : 0] = 0;
        degree_approx_reg[0] = 0;
        arctan_en_reg[0] = arctan_en_in;
        sector_reg[0] = sector_in;
        valid_reg[0] = valid_in;
        if (arctan_en_in) begin
           x_reg[0][ITERATION_WORD_FRAC_WIDTH + UNSIGNED_INPUT_INT_WIDTH - 1 : ITERATION_WORD_FRAC_WIDTH - UNSIGNED_INPUT_FRAC_WIDTH] = x_in;
           x_reg[0][ITERATION_WORD_WIDTH - 1 : ITERATION_WORD_FRAC_WIDTH + UNSIGNED_INPUT_INT_WIDTH] = 0;
           x_reg[0][ITERATION_WORD_FRAC_WIDTH - UNSIGNED_INPUT_FRAC_WIDTH - 1 : 0] = 0;
           y_reg[0][ITERATION_WORD_FRAC_WIDTH + UNSIGNED_INPUT_INT_WIDTH - 1 : ITERATION_WORD_FRAC_WIDTH - UNSIGNED_INPUT_FRAC_WIDTH] = y_in;
           y_reg[0][ITERATION_WORD_WIDTH - 1 : ITERATION_WORD_FRAC_WIDTH + UNSIGNED_INPUT_INT_WIDTH] = 0;
           y_reg[0][ITERATION_WORD_FRAC_WIDTH - UNSIGNED_INPUT_FRAC_WIDTH - 1 : 0] = 0;
        end
        else begin
           // x_reg[0] = 32'b000000000001 00000000000000000000;
           x_reg[0] = 32'b00000000000100000000000000000000;
           y_reg[0] = 0;
        end
     end

   generate
      genvar i;
      for(i = 1; i < ITERATION_NUMBER + 1; i = i + 1)
        begin
           always @ (posedge clk or negedge reset) begin
              if(!reset) begin
                 degree_reg[i] <= 0;
                 degree_approx_reg[i] <= 0;
                 x_reg[i] <= 0;
                 y_reg[i] <= 0;
                 arctan_en_reg[i] <= 0;
                 sector_reg[i] <= 0;
                 valid_reg[i] <= 0;
              end
              else
                if (arctan_en_reg[i - 1]) begin
                   arctan_en_reg[i] <= 1;
                   if (y_reg[i - 1] > 0) begin
                      degree_approx_reg[i] <= degree_approx_reg[i - 1] + degree_mem[i - 1];
                      x_reg[i] <= x_reg[i - 1] + (y_reg[i - 1] >>> (i - 1));
                      y_reg[i] <= y_reg[i - 1] - (x_reg[i - 1] >>> (i - 1));
                   end
                   else begin
                      degree_approx_reg[i] <= degree_approx_reg[i - 1] - degree_mem[i - 1];
                      x_reg[i] <= x_reg[i - 1] - (y_reg[i - 1] >>> (i - 1));
                      y_reg[i] <= y_reg[i - 1] + (x_reg[i - 1] >>> (i - 1));
                   end
                end
                else begin
                   arctan_en_reg[i] <= 0;
                   if (degree_approx_reg[i - 1] > degree_reg[i - 1]) begin
                      degree_approx_reg[i] <= degree_approx_reg[i - 1] - degree_mem[i - 1];
                      x_reg[i] <= x_reg[i - 1] + (y_reg[i - 1] >>> (i - 1));
                      y_reg[i] <= y_reg[i - 1] - (x_reg[i - 1] >>> (i - 1));
                   end
                   else begin
                      degree_approx_reg[i] <= degree_approx_reg[i - 1] + degree_mem[i - 1];
                      x_reg[i] <= x_reg[i - 1] - (y_reg[i - 1] >>> (i - 1));
                      y_reg[i] <= y_reg[i - 1] + (x_reg[i - 1] >>> (i - 1));
                   end
                end
              degree_reg[i] <= degree_reg[i - 1];
              sector_reg[i] <= sector_reg[i - 1];
              valid_reg[i] <= valid_reg[i - 1];
           end
        end
   endgenerate

   /*
    k = 0.1001101101111011011001111101010111101100101100001111100111101011001100011000010111000110000010110101
    */
   wire signed [ITERATION_WORD_WIDTH * 2 - 1 : 0] k_reg;
   wire signed [ITERATION_WORD_WIDTH * 2 - 1 : 0] x_enlarge_reg;
   wire signed [ITERATION_WORD_WIDTH * 2 - 1 : 0] y_enlarge_reg;
   // k_reg = 64'b00000000000000000000000000000000 000000000000 10011011011110110110;
   // for N = 14, k = 0.10011011011101001110110110101110101111011001001011110
   assign k_reg = 64'b0000000000000000000000000000000000000000000010011011011110110110;
   generate
      genvar                                      j;
      for(j = ITERATION_WORD_WIDTH; j < ITERATION_WORD_WIDTH * 2; j = j + 1) begin
         assign x_enlarge_reg[j] = x_reg[ITERATION_NUMBER][ITERATION_WORD_WIDTH - 1];
         assign y_enlarge_reg[j] = y_reg[ITERATION_NUMBER][ITERATION_WORD_WIDTH - 1];
      end
   endgenerate
   assign x_enlarge_reg[ITERATION_WORD_WIDTH - 1 : 0] = x_reg[ITERATION_NUMBER][ITERATION_WORD_WIDTH - 2 : 0];
   assign y_enlarge_reg[ITERATION_WORD_WIDTH - 1 : 0] = y_reg[ITERATION_NUMBER][ITERATION_WORD_WIDTH - 2 : 0];


   reg signed [ITERATION_WORD_WIDTH * 2 - 1 : 0]  x_correct_reg;
   reg signed [ITERATION_WORD_WIDTH * 2 - 1 : 0]  y_correct_reg;
   always @ * begin
      x_correct_reg = (x_enlarge_reg * k_reg) >>> 22;
      y_correct_reg = (y_enlarge_reg * k_reg) >>> 22;
   end

   assign degree_out[UNSIGNED_OUTPUT_WIDTH - 1 : 0]
     = degree_approx_reg[ITERATION_NUMBER]
       [ITERATION_WORD_FRAC_WIDTH + UNSIGNED_INPUT_INT_WIDTH - 1 : ITERATION_WORD_FRAC_WIDTH - UNSIGNED_INPUT_FRAC_WIDTH];
   assign x_out[UNSIGNED_OUTPUT_WIDTH - 1] = x_correct_reg[ITERATION_WORD_WIDTH * 2 - 1];
   assign x_out[UNSIGNED_OUTPUT_WIDTH - 2 : 0]
     = x_correct_reg
       [ITERATION_WORD_FRAC_WIDTH + UNSIGNED_INPUT_INT_WIDTH - 2 : ITERATION_WORD_FRAC_WIDTH - UNSIGNED_INPUT_FRAC_WIDTH];
   assign y_out[UNSIGNED_OUTPUT_WIDTH - 1] = y_correct_reg[ITERATION_WORD_WIDTH * 2 - 1];
   assign y_out[UNSIGNED_OUTPUT_WIDTH - 2 : 0]
     = y_correct_reg
       [ITERATION_WORD_FRAC_WIDTH + UNSIGNED_INPUT_INT_WIDTH - 2 : ITERATION_WORD_FRAC_WIDTH - UNSIGNED_INPUT_FRAC_WIDTH];
   assign arctan_en_out
     = arctan_en_reg[ITERATION_NUMBER];
   assign sector_out
     =sector_reg[ITERATION_NUMBER];
   assign valid_out
     =valid_reg[ITERATION_NUMBER];
endmodule // pipeline

HDL/core/tb.v
`include "pipeline.v"
`timescale 1ns/1ns
`define SIM_TIME 118600

module tb#(
           parameter UNSIGNED_INPUT_WIDTH = 16,
           parameter UNSIGNED_OUTPUT_WIDTH = 16,
           parameter UNSIGNED_INPUT_INT_WIDTH = 7,
           parameter UNSIGNED_INPUT_FRAC_WIDTH = 8,
           parameter UNSIGNED_OUTPUT_INT_WIDTH = 7,
           parameter UNSIGNED_OUTPUT_FRAC_WIDTH = 8,
           parameter ITERATION_NUMBER = 6,
           parameter ITERATION_WORD_WIDTH = 32,
           parameter ITERATION_WORD_INT_WIDTH = 12,
           parameter ITERATION_WORD_FRAC_WIDTH = 20,
           parameter SECTOR_FLAG_WIDTH = 2
           )();
   reg               clk;
   reg               reset;
   initial begin
      degree_in_reg = 0;
      clk = 0;
      reset = 0;
      $dumpfile("tb.vcd");
      $dumpvars(0, tb.clk);
      $dumpvars(0, tb.reset);
      $dumpvars(0, tb.x_out);
      $dumpvars(0, tb.y_out);
      $dumpvars(0, tb.degree_out);
      $dumpvars(0, tb.degree_in);

      for(integer i = 0; i < ITERATION_NUMBER + 1; i = i + 1)
        begin
           $dumpvars(0, tb.pipeline.degree_reg[i]);
           $dumpvars(0, tb.pipeline.degree_approx_reg[i]);
           $dumpvars(0, tb.pipeline.x_reg[i]);
           $dumpvars(0, tb.pipeline.y_reg[i]);
           if (i < ITERATION_NUMBER)
             $dumpvars(0, tb.pipeline.degree_mem[i]);
        end
      $dumpvars(0, tb.pipeline.k_reg);
      $dumpvars(0, tb.pipeline.x_correct_reg);
      $dumpvars(0, tb.pipeline.y_correct_reg);
      $dumpvars(0, tb.pipeline.y_enlarge_reg);
      $dumpvars(0, tb.pipeline.x_enlarge_reg);
      #5 reset = 1;
      # `SIM_TIME $finish;
   end
   always #10 clk = !clk;
   reg [UNSIGNED_INPUT_WIDTH - 1 : 0] degree_in_reg;
   always @ (posedge clk)
     begin
        degree_in_reg <= degree_in_reg + 16'b0000000000010000;
     end
   wire [UNSIGNED_OUTPUT_WIDTH - 1 : 0] degree_out;
   wire [UNSIGNED_OUTPUT_WIDTH - 1 : 0] x_out;
   wire [UNSIGNED_OUTPUT_WIDTH - 1 : 0] y_out;
   wire [UNSIGNED_INPUT_WIDTH - 1 : 0]  degree_in;
   wire [SECTOR_FLAG_WIDTH - 1 : 0]     sector_in;
   wire [SECTOR_FLAG_WIDTH - 1 : 0]     sector_out;
   wire                                 arctan_en_in;
   wire                                 arctan_en_out;
   wire [UNSIGNED_INPUT_WIDTH - 1 : 0]  x_in;
   wire [UNSIGNED_INPUT_WIDTH - 1 : 0]  y_in;
   assign degree_in = degree_in_reg;
   assign arctan_en_in = 1;
   assign x_in = 16'b0000000100000000;
   assign y_in = 16'b0000000110111011;
   pipeline pipeline(/*AUTOINST*/
                     // Outputs
                     .degree_out        (degree_out),
                     .x_out             (x_out),
                     .y_out             (y_out),
                     .sector_out        (sector_out),
                     .arctan_en_out     (arctan_en_out),
                     // Inputs
                     .clk               (clk),
                     .reset             (reset),
                     .degree_in         (degree_in),
                     .x_in              (x_in),
                     .y_in              (y_in),
                     .sector_in         (sector_in),
                     .arctan_en_in      (arctan_en_in));
endmodule // tb

HDL/core/tb.vcd
$date
	Mon May 31 02:01:21 2021
$end
$version
	Icarus Verilog
$end
$timescale
	1ns
$end
$scope module tb $end
$var reg 1 ! clk $end
$upscope $end
$scope module tb $end
$var reg 1 " reset $end
$upscope $end
$scope module tb $end
$var wire 16 # x_out [15:0] $end
$upscope $end
$scope module tb $end
$var wire 16 $ y_out [15:0] $end
$upscope $end
$scope module tb $end
$var wire 16 % degree_out [15:0] $end
$upscope $end
$scope module tb $end
$var wire 16 & degree_in [15:0] $end
$upscope $end
$scope module tb $end
$scope module pipeline $end
$var reg 231 ' degree_reg [230:0] $end
$upscope $end
$upscope $end
$scope module tb $end
$scope module pipeline $end
$var reg 231 ( degree_approx_reg [230:0] $end
$upscope $end
$upscope $end
$scope module tb $end
$scope module pipeline $end
$var reg 231 ) x_reg [230:0] $end
$upscope $end
$upscope $end
$scope module tb $end
$scope module pipeline $end
$var reg 231 * y_reg [230:0] $end
$upscope $end
$upscope $end
$scope module tb $end
$scope module pipeline $end
$var wire 33 + k_reg [32:0] $end
$upscope $end
$upscope $end
$enddefinitions $end
#0
$dumpvars
b100100010101100011100111011100111 +
b0 *
b101111101011110000100000000 )
b0 (
b110010100000000000000000000000000 '
b110010100000000 &
b0 %
b0 $
b0 #
0"
0!
$end
#5
1"
#10
b110011001100110 %
b110010100000000000000000000000000110010100000000000000000000000000 '
b10111110101111000010000000000000000000000000000000000000000 *
b101111101011110000100000000000000101111101011110000100000000 )
b110011001100110101100111101011011100101010001100110001001101111001000100110100110110010101000101001100000100111000101011110100000001000111000011000000011010100101110100010100000000000000000000000000000000000000000000000000000000000 (
1!
#20
0!
#30
b110010000100110 %
b110010100000000000000000000000000110010100000000000000000000000000110010100000000000000000000000000 '
b100011110000110100011000000000000010111110101111000010000000000000000000000000000000000000000 *
b101001101110010010011100000000000101111101011110000100000000000000101111101011110000100000000 )
b110010000100110000100010000011110011111100011010000001011010110000011011110010001111001001011011000100110011011111010111100000101101101001100011000000011010100101110100010100000000000000000000000000000000000000000000000000000000000 (
1!
#40
0!
#50
b101100010110011 %
b110010100000000000000000000000000110010100000000000000000000000000110010100000000000000000000000000110010100000000000000000000000000 '
b101000111110100110101011100000000100011110000110100011000000000000010111110101111000010000000000000000000000000000000000000000 *
b100101010000001011111001000000000101001101110010010011100000000000101111101011110000100000000000000101111101011110000100000000 )
b101100010110011010100011101010101110110100000101000111111101011111100001100111000100100111000000100001010001010000101111001000101111101001100011000000011010100101110100010100000000000000000000000000000000000000000000000000000000000 (
1!
#60
0!
#70
b11010011110 %
b110010100000000000000000000000000110010100000000000000000000000000110010100000000000000000000000000110010100000000000000000000000000110010100000000000000000000000000 '
b101011010011100111011011000000000101000111110100110101011100000000100011110000110100011000000000000010111110101111000010000000000000000000000000000000000000000 *
b100010101100010001011110011000000100101010000001011111001000000000101001101110010010011100000000000101111101011110000100000000000000101111101011110000100000000 )
b11010011110011011000000000100111100010101011110011101010001011001110111110111100001110001011000001010001010000101111001000101111101001100011000000011010100101110100010100000000000000000000000000000000000000000000000000000000000 (
1!
#80
0!
#90
b1001001000101 %
b110010100000000000000000000000000110010100000000000000000000000000110010100000000000000000000000000110010100000000000000000000000000110010100000000000000000000000000110010100000000000000000000000000 '
b101100011000111111111101111000000101011010011100111011011000000000101000111110100110101011100000000100011110000110100011000000000000010111110101111000010000000000000000000000000000000000000000 *
b100001010101101010001111101000000100010101100010001011110011000000100101010000001011111001000000000101001101110010010011100000000000101111101011110000100000000000000101111101011110000100000000 )
b1001001000101000110101100110000110100010000100010010111111010001001110111110111100001110001011000001010001010000101111001000101111101001100011000000011010100101110100010100000000000000000000000000000000000000000000000000000000000 (
1!
#100
0!
#110
b110010101000100 $
b11101101000 #
b1000011101 %
b110010100000000000000000000000000110010100000000000000000000000000110010100000000000000000000000000110010100000000000000000000000000110010100000000000000000000000000110010100000000000000000000000000110010100000000000000000000000000 '
b101011110111101010010011110000000101100011000111111111101111000000101011010011100111011011000000000101000111110100110101011100000000100011110000110100011000000000000010111110101111000010000000000000000000000000000000000000000 *
b100010000010000011001111100000000100001010101101010001111101000000100010101100010001011110011000000100101010000001011111001000000000101001101110010010011100000000000101111101011110000100000000000000101111101011110000100000000 )
b1000011101100110000001110110110100010000100010010111111010001001110111110111100001110001011000001010001010000101111001000101111101001100011000000011010100101110100010100000000000000000000000000000000000000000000000000000000000 (
1!
